edmclient/__init__.py
edmclient/alerts.py
edmclient/configuration.py
edmclient/cti.py
edmclient/devices.py
edmclient/edm.py
edmclient/exceptions.py
edmclient/rest_methods.py
edmclient/traffic.py
edm_client-1.1.0.dist-info/LICENSE
edm_client-1.1.0.dist-info/METADATA
edm_client-1.1.0.dist-info/WHEEL
edm_client-1.1.0.dist-info/top_level.txt
edm_client-1.1.0.dist-info/RECORD
