Metadata-Version: 2.1
Name: edm-client
Version: 1.1.0
Summary: Edge Defense Manager Client
Home-page: UNKNOWN
Author: Steve William, NETSCOUT Systems, Inc.
Author-email: swilliam@netscout.com
License: MIT
Platform: UNKNOWN
Classifier: Operating System :: OS Independent
Classifier: License :: OSI Approved :: MIT License
Classifier: Programming Language :: Python
Requires-Dist: requests
